osx_tags/__init__.py
osx_tags/cmd.py
osx_tags-0.1.3.dist-info/DESCRIPTION.rst
osx_tags-0.1.3.dist-info/METADATA
osx_tags-0.1.3.dist-info/RECORD
osx_tags-0.1.3.dist-info/WHEEL
osx_tags-0.1.3.dist-info/entry_points.txt
osx_tags-0.1.3.dist-info/metadata.json
osx_tags-0.1.3.dist-info/top_level.txt
osx_tags-0.1.3.dist-info/zip-safe
