Metadata-Version: 2.0
Name: osx-tags
Version: 0.1.3
Summary: Module to manipulate Finder tags on OS X
Home-page: https://github.com/scooby/osx-tags
Author: UNKNOWN
Author-email: UNKNOWN
License: MIT
Platform: UNKNOWN
Classifier: Programming Language :: Python :: 2
Classifier: Programming Language :: Python :: 3
Requires-Dist: biplist
Requires-Dist: xattr
Provides-Extra: click
Requires-Dist: click; extra == 'click'
